<?xml version="1.0" encoding="UTF-8"?>
<zabbix_export>
    <version>3.2</version>
    <date>2017-09-25T13:22:04Z</date>
    <groups>
        <group>
            <name>Linux Server's</name>
        </group>
    </groups>
    <templates>
        <template>
            <template>PBX template</template>
            <name>PBX template</name>
            <description/>
            <groups>
                <group>
                    <name>Linux Server's</name>
                </group>
            </groups>
            <applications/>
            <items>
                <item>
                    <name>Call Per Day</name>
                    <type>0</type>
                    <snmp_community/>
                    <multiplier>0</multiplier>
                    <snmp_oid/>
                    <key>ans_call</key>
                    <delay>10</delay>
                    <history>30</history>
                    <trends>90</trends>
                    <status>0</status>
                    <value_type>3</value_type>
                    <allowed_hosts/>
                    <units/>
                    <delta>0</delta>
                    <snmpv3_contextname/>
                    <snmpv3_securityname/>
                    <snmpv3_securitylevel>0</snmpv3_securitylevel>
                    <snmpv3_authprotocol>0</snmpv3_authprotocol>
                    <snmpv3_authpassphrase/>
                    <snmpv3_privprotocol>0</snmpv3_privprotocol>
                    <snmpv3_privpassphrase/>
                    <formula>1</formula>
                    <delay_flex/>
                    <params/>
                    <ipmi_sensor/>
                    <data_type>0</data_type>
                    <authtype>0</authtype>
                    <username/>
                    <password/>
                    <publickey/>
                    <privatekey/>
                    <port/>
                    <description/>
                    <inventory_link>0</inventory_link>
                    <applications/>
                    <valuemap/>
                    <logtimefmt/>
                </item>
                <item>
                    <name>Dropped Call's</name>
                    <type>0</type>
                    <snmp_community/>
                    <multiplier>0</multiplier>
                    <snmp_oid/>
                    <key>dropcall</key>
                    <delay>600</delay>
                    <history>30</history>
                    <trends>90</trends>
                    <status>0</status>
                    <value_type>3</value_type>
                    <allowed_hosts/>
                    <units/>
                    <delta>0</delta>
                    <snmpv3_contextname/>
                    <snmpv3_securityname/>
                    <snmpv3_securitylevel>0</snmpv3_securitylevel>
                    <snmpv3_authprotocol>0</snmpv3_authprotocol>
                    <snmpv3_authpassphrase/>
                    <snmpv3_privprotocol>0</snmpv3_privprotocol>
                    <snmpv3_privpassphrase/>
                    <formula>1</formula>
                    <delay_flex/>
                    <params/>
                    <ipmi_sensor/>
                    <data_type>0</data_type>
                    <authtype>0</authtype>
                    <username/>
                    <password/>
                    <publickey/>
                    <privatekey/>
                    <port/>
                    <description/>
                    <inventory_link>0</inventory_link>
                    <applications/>
                    <valuemap/>
                    <logtimefmt/>
                </item>
                <item>
                    <name>Sip Channel Usage</name>
                    <type>0</type>
                    <snmp_community/>
                    <multiplier>0</multiplier>
                    <snmp_oid/>
                    <key>sip</key>
                    <delay>5</delay>
                    <history>30</history>
                    <trends>90</trends>
                    <status>0</status>
                    <value_type>3</value_type>
                    <allowed_hosts/>
                    <units>channel</units>
                    <delta>0</delta>
                    <snmpv3_contextname/>
                    <snmpv3_securityname/>
                    <snmpv3_securitylevel>0</snmpv3_securitylevel>
                    <snmpv3_authprotocol>0</snmpv3_authprotocol>
                    <snmpv3_authpassphrase/>
                    <snmpv3_privprotocol>0</snmpv3_privprotocol>
                    <snmpv3_privpassphrase/>
                    <formula>1</formula>
                    <delay_flex/>
                    <params/>
                    <ipmi_sensor/>
                    <data_type>0</data_type>
                    <authtype>0</authtype>
                    <username/>
                    <password/>
                    <publickey/>
                    <privatekey/>
                    <port/>
                    <description/>
                    <inventory_link>0</inventory_link>
                    <applications/>
                    <valuemap/>
                    <logtimefmt/>
                </item>
                <item>
                    <name>SLA</name>
                    <type>0</type>
                    <snmp_community/>
                    <multiplier>0</multiplier>
                    <snmp_oid/>
                    <key>sla</key>
                    <delay>300</delay>
                    <history>30</history>
                    <trends>90</trends>
                    <status>0</status>
                    <value_type>0</value_type>
                    <allowed_hosts/>
                    <units>%</units>
                    <delta>0</delta>
                    <snmpv3_contextname/>
                    <snmpv3_securityname/>
                    <snmpv3_securitylevel>0</snmpv3_securitylevel>
                    <snmpv3_authprotocol>0</snmpv3_authprotocol>
                    <snmpv3_authpassphrase/>
                    <snmpv3_privprotocol>0</snmpv3_privprotocol>
                    <snmpv3_privpassphrase/>
                    <formula>1</formula>
                    <delay_flex/>
                    <params/>
                    <ipmi_sensor/>
                    <data_type>0</data_type>
                    <authtype>0</authtype>
                    <username/>
                    <password/>
                    <publickey/>
                    <privatekey/>
                    <port/>
                    <description/>
                    <inventory_link>0</inventory_link>
                    <applications/>
                    <valuemap/>
                    <logtimefmt/>
                </item>
                <item>
                    <name>Sip Trunk down</name>
                    <type>0</type>
                    <snmp_community/>
                    <multiplier>0</multiplier>
                    <snmp_oid/>
                    <key>trunkdown</key>
                    <delay>5</delay>
                    <history>30</history>
                    <trends>90</trends>
                    <status>0</status>
                    <value_type>3</value_type>
                    <allowed_hosts/>
                    <units/>
                    <delta>0</delta>
                    <snmpv3_contextname/>
                    <snmpv3_securityname/>
                    <snmpv3_securitylevel>0</snmpv3_securitylevel>
                    <snmpv3_authprotocol>0</snmpv3_authprotocol>
                    <snmpv3_authpassphrase/>
                    <snmpv3_privprotocol>0</snmpv3_privprotocol>
                    <snmpv3_privpassphrase/>
                    <formula>1</formula>
                    <delay_flex/>
                    <params/>
                    <ipmi_sensor/>
                    <data_type>0</data_type>
                    <authtype>0</authtype>
                    <username/>
                    <password/>
                    <publickey/>
                    <privatekey/>
                    <port/>
                    <description/>
                    <inventory_link>0</inventory_link>
                    <applications/>
                    <valuemap/>
                    <logtimefmt/>
                </item>
                <item>
                    <name>Active Waiting Call's</name>
                    <type>0</type>
                    <snmp_community/>
                    <multiplier>0</multiplier>
                    <snmp_oid/>
                    <key>waitin</key>
                    <delay>5</delay>
                    <history>30</history>
                    <trends>90</trends>
                    <status>0</status>
                    <value_type>3</value_type>
                    <allowed_hosts/>
                    <units/>
                    <delta>0</delta>
                    <snmpv3_contextname/>
                    <snmpv3_securityname/>
                    <snmpv3_securitylevel>0</snmpv3_securitylevel>
                    <snmpv3_authprotocol>0</snmpv3_authprotocol>
                    <snmpv3_authpassphrase/>
                    <snmpv3_privprotocol>0</snmpv3_privprotocol>
                    <snmpv3_privpassphrase/>
                    <formula>1</formula>
                    <delay_flex/>
                    <params/>
                    <ipmi_sensor/>
                    <data_type>0</data_type>
                    <authtype>0</authtype>
                    <username/>
                    <password/>
                    <publickey/>
                    <privatekey/>
                    <port/>
                    <description/>
                    <inventory_link>0</inventory_link>
                    <applications/>
                    <valuemap/>
                    <logtimefmt/>
                </item>
            </items>
            <discovery_rules/>
            <httptests/>
            <macros/>
            <templates/>
            <screens/>
        </template>
    </templates>
    <triggers>
        <trigger>
            <expression>{PBX template:trunkdown.last(#3)}=0</expression>
            <recovery_mode>0</recovery_mode>
            <recovery_expression/>
            <name>Sip Trunk Down</name>
            <correlation_mode>0</correlation_mode>
            <correlation_tag/>
            <url/>
            <status>0</status>
            <priority>5</priority>
            <description/>
            <type>0</type>
            <manual_close>0</manual_close>
            <dependencies/>
            <tags/>
        </trigger>
        <trigger>
            <expression>{PBX template:sip.last(,60)}&gt;10 and {PBX template:sip.last(,60)}&lt;20</expression>
            <recovery_mode>0</recovery_mode>
            <recovery_expression/>
            <name>Sip Trunk Down {HOST.NAME}</name>
            <correlation_mode>0</correlation_mode>
            <correlation_tag/>
            <url/>
            <status>0</status>
            <priority>2</priority>
            <description/>
            <type>0</type>
            <manual_close>0</manual_close>
            <dependencies/>
            <tags/>
        </trigger>
        <trigger>
            <expression>{PBX template:sip.last(,60)}&gt;20 and {PBX template:sip.last(,60)}&lt;30</expression>
            <recovery_mode>0</recovery_mode>
            <recovery_expression/>
            <name>Sip Trunk Down {HOST.NAME}</name>
            <correlation_mode>0</correlation_mode>
            <correlation_tag/>
            <url/>
            <status>0</status>
            <priority>3</priority>
            <description/>
            <type>0</type>
            <manual_close>0</manual_close>
            <dependencies/>
            <tags/>
        </trigger>
        <trigger>
            <expression>{PBX template:sip.last(,60)}&gt;40 and {PBX template:sip.last(,60)}&lt;45</expression>
            <recovery_mode>0</recovery_mode>
            <recovery_expression/>
            <name>Sip Trunk Down {HOST.NAME}</name>
            <correlation_mode>0</correlation_mode>
            <correlation_tag/>
            <url/>
            <status>0</status>
            <priority>4</priority>
            <description/>
            <type>0</type>
            <manual_close>0</manual_close>
            <dependencies/>
            <tags/>
        </trigger>
    </triggers>
    <graphs>
        <graph>
            <name>All call</name>
            <width>500</width>
            <height>500</height>
            <yaxismin>0.0000</yaxismin>
            <yaxismax>0.0000</yaxismax>
            <show_work_period>0</show_work_period>
            <show_triggers>0</show_triggers>
            <type>2</type>
            <show_legend>1</show_legend>
            <show_3d>1</show_3d>
            <percent_left>0.0000</percent_left>
            <percent_right>0.0000</percent_right>
            <ymin_type_1>0</ymin_type_1>
            <ymax_type_1>0</ymax_type_1>
            <ymin_item_1>0</ymin_item_1>
            <ymax_item_1>0</ymax_item_1>
            <graph_items>
                <graph_item>
                    <sortorder>0</sortorder>
                    <drawtype>0</drawtype>
                    <color>1A7C11</color>
                    <yaxisside>0</yaxisside>
                    <calc_fnc>2</calc_fnc>
                    <type>0</type>
                    <item>
                        <host>PBX template</host>
                        <key>ans_call</key>
                    </item>
                </graph_item>
                <graph_item>
                    <sortorder>1</sortorder>
                    <drawtype>0</drawtype>
                    <color>F63100</color>
                    <yaxisside>0</yaxisside>
                    <calc_fnc>2</calc_fnc>
                    <type>0</type>
                    <item>
                        <host>PBX template</host>
                        <key>dropcall</key>
                    </item>
                </graph_item>
            </graph_items>
        </graph>
        <graph>
            <name>Call Per Day</name>
            <width>900</width>
            <height>200</height>
            <yaxismin>0.0000</yaxismin>
            <yaxismax>100.0000</yaxismax>
            <show_work_period>1</show_work_period>
            <show_triggers>1</show_triggers>
            <type>0</type>
            <show_legend>1</show_legend>
            <show_3d>0</show_3d>
            <percent_left>0.0000</percent_left>
            <percent_right>0.0000</percent_right>
            <ymin_type_1>0</ymin_type_1>
            <ymax_type_1>0</ymax_type_1>
            <ymin_item_1>0</ymin_item_1>
            <ymax_item_1>0</ymax_item_1>
            <graph_items>
                <graph_item>
                    <sortorder>0</sortorder>
                    <drawtype>0</drawtype>
                    <color>1A7C11</color>
                    <yaxisside>0</yaxisside>
                    <calc_fnc>2</calc_fnc>
                    <type>0</type>
                    <item>
                        <host>PBX template</host>
                        <key>ans_call</key>
                    </item>
                </graph_item>
            </graph_items>
        </graph>
        <graph>
            <name>Dropped Call's</name>
            <width>900</width>
            <height>200</height>
            <yaxismin>0.0000</yaxismin>
            <yaxismax>100.0000</yaxismax>
            <show_work_period>1</show_work_period>
            <show_triggers>1</show_triggers>
            <type>0</type>
            <show_legend>1</show_legend>
            <show_3d>0</show_3d>
            <percent_left>0.0000</percent_left>
            <percent_right>0.0000</percent_right>
            <ymin_type_1>0</ymin_type_1>
            <ymax_type_1>0</ymax_type_1>
            <ymin_item_1>0</ymin_item_1>
            <ymax_item_1>0</ymax_item_1>
            <graph_items>
                <graph_item>
                    <sortorder>0</sortorder>
                    <drawtype>0</drawtype>
                    <color>1A7C11</color>
                    <yaxisside>0</yaxisside>
                    <calc_fnc>2</calc_fnc>
                    <type>0</type>
                    <item>
                        <host>PBX template</host>
                        <key>dropcall</key>
                    </item>
                </graph_item>
            </graph_items>
        </graph>
        <graph>
            <name>Sip Channel Usage</name>
            <width>900</width>
            <height>200</height>
            <yaxismin>0.0000</yaxismin>
            <yaxismax>100.0000</yaxismax>
            <show_work_period>1</show_work_period>
            <show_triggers>1</show_triggers>
            <type>0</type>
            <show_legend>1</show_legend>
            <show_3d>0</show_3d>
            <percent_left>0.0000</percent_left>
            <percent_right>0.0000</percent_right>
            <ymin_type_1>0</ymin_type_1>
            <ymax_type_1>0</ymax_type_1>
            <ymin_item_1>0</ymin_item_1>
            <ymax_item_1>0</ymax_item_1>
            <graph_items>
                <graph_item>
                    <sortorder>0</sortorder>
                    <drawtype>0</drawtype>
                    <color>1A7C11</color>
                    <yaxisside>0</yaxisside>
                    <calc_fnc>2</calc_fnc>
                    <type>0</type>
                    <item>
                        <host>PBX template</host>
                        <key>sip</key>
                    </item>
                </graph_item>
            </graph_items>
        </graph>
        <graph>
            <name>SLA</name>
            <width>900</width>
            <height>200</height>
            <yaxismin>0.0000</yaxismin>
            <yaxismax>100.0000</yaxismax>
            <show_work_period>1</show_work_period>
            <show_triggers>1</show_triggers>
            <type>0</type>
            <show_legend>1</show_legend>
            <show_3d>0</show_3d>
            <percent_left>0.0000</percent_left>
            <percent_right>0.0000</percent_right>
            <ymin_type_1>0</ymin_type_1>
            <ymax_type_1>0</ymax_type_1>
            <ymin_item_1>0</ymin_item_1>
            <ymax_item_1>0</ymax_item_1>
            <graph_items>
                <graph_item>
                    <sortorder>0</sortorder>
                    <drawtype>0</drawtype>
                    <color>1A7C11</color>
                    <yaxisside>0</yaxisside>
                    <calc_fnc>2</calc_fnc>
                    <type>0</type>
                    <item>
                        <host>PBX template</host>
                        <key>sla</key>
                    </item>
                </graph_item>
            </graph_items>
        </graph>
    </graphs>
</zabbix_export>
